{
  "version": "0.0.3",
  "job_config": {
    "version": "0.0.3",
    "name": null,
    "steps": [
      {
        "type": "udf",
        "udf": {
          "type": "geopandas_v2",
          "name": "my_main",
          "entrypoint": "udf",
          "parameters": {},
          "metadata": {
            "fused:name": "my_main",
            "fused:slug": "my_main",
            "fused:gitRepo": "fusedio/udfs",
            "fused:gitRef": "92ece07f346dea9d85129db8294d5a03124145ae",
            "fused:gitUrl": "https://github.com/fusedio/udfs/tree/92ece07f346dea9d85129db8294d5a03124145ae/community/sina/my_main/",
            "fused:gitShortUrl": "https://github.com/fusedio/udfs/tree/92ece07/community/sina/my_main/",
            "fused:gitPath": "community/sina/my_main",
            "fused:gitLastModified": "2025-03-24T19:53:54+00:00",
            "fused:gitPullRequestBranch": "sina-patch-06434d-fix-global-issye",
            "fused:gitPullRequestLink": "https://github.com/fusedlabs/fusedudfs/pull/632",
            "fused:vizConfig": {
              "tileLayer": {
                "@@type": "TileLayer",
                "minZoom": 0,
                "maxZoom": 19,
                "tileSize": 256
              },
              "rasterLayer": {
                "@@type": "BitmapLayer",
                "pickable": true
              },
              "vectorLayer": {
                "@@type": "GeoJsonLayer",
                "stroked": true,
                "filled": false,
                "pickable": true,
                "lineWidthMinPixels": 1,
                "pointRadiusMinPixels": 1,
                "getLineColor": {
                  "@@function": "colorContinuous",
                  "attr": "value",
                  "domain": [
                    0,
                    10
                  ],
                  "steps": 20,
                  "colors": "BluYl",
                  "nullColor": [
                    184,
                    184,
                    184
                  ]
                },
                "getFillColor": [
                  208,
                  208,
                  208,
                  40
                ]
              }
            },
            "fused:udfType": "auto",
            "fused:id": null,
            "fused:description": "Exported from Fused UDF Workbench\n\n",
            "fused:gitAuthorNames": [
              "Sina Kashuk"
            ],
            "fused:gitAuthorUsernames": [
              "kashuk"
            ],
            "fused:gitAuthorUrls": [
              "https://github.com/kashuk"
            ],
            "fused:gitAuthorAvatarUrls": [
              "https://avatars.githubusercontent.com/u/12432685?v=4"
            ],
            "fused:explorerTab": "community"
          },
          "source": "my_main.py",
          "headers": []
        }
      }
    ],
    "metadata": null
  }
}