{
  "version": "0.0.3",
  "job_config": {
    "version": "0.0.3",
    "name": null,
    "steps": [
      {
        "type": "udf",
        "udf": {
          "type": "geopandas_v2",
          "name": "copper_pinniped",
          "entrypoint": "udf",
          "parameters": {},
          "metadata": {
            "fused:name": "copper_pinniped",
            "fused:slug": "copper_pinniped",
            "fused:gitRepo": "fusedio/udfs",
            "fused:gitRef": "e4d3202f6f72e34f93170678bc7660539e558adc",
            "fused:gitUrl": "https://github.com/fusedio/udfs/tree/e4d3202f6f72e34f93170678bc7660539e558adc/public/copper_pinniped/",
            "fused:gitShortUrl": "https://github.com/fusedio/udfs/tree/e4d3202/public/copper_pinniped/",
            "fused:gitPath": "public/copper_pinniped",
            "fused:gitLastModified": "2024-12-05T21:43:45.313Z",
            "fused:gitPullRequestBranch": "chloe@fused.io-patch-test",
            "fused:gitPullRequestLink": "https://github.com/fusedio/udfs/pull/481",
            "fused:vizConfig": {
              "tileLayer": {
                "@@type": "TileLayer",
                "minZoom": 0,
                "maxZoom": 19,
                "tileSize": 256,
                "pickable": true
              },
              "rasterLayer": {
                "@@type": "BitmapLayer",
                "pickable": true
              },
              "vectorLayer": {
                "@@type": "GeoJsonLayer",
                "stroked": true,
                "filled": false,
                "pickable": true,
                "lineWidthMinPixels": 1,
                "pointRadiusMinPixels": 1,
                "getLineColor": {
                  "@@function": "colorContinuous",
                  "attr": "value",
                  "domain": [
                    0,
                    10
                  ],
                  "colors": "Peach",
                  "nullColor": [
                    184,
                    184,
                    184
                  ]
                },
                "getFillColor": [
                  208,
                  208,
                  208,
                  40
                ]
              }
            },
            "fused:udfType": "auto",
            "fused:id": null
          },
          "source": "copper_pinniped.py",
          "headers": []
        }
      }
    ],
    "metadata": null
  }
}